case_utils/__init__.py
case_utils/inherent_uuid.py
case_utils/namespace.py
case_utils/py.typed
case_utils/case_file/__init__.py
case_utils/case_sparql_construct/__init__.py
case_utils/case_sparql_select/__init__.py
case_utils/case_validate/__init__.py
case_utils/case_validate/validate_types.py
case_utils/case_validate/validate_utils.py
case_utils/ontology/__init__.py
case_utils/ontology/case-0.5.0-subclasses.ttl
case_utils/ontology/case-0.5.0.ttl
case_utils/ontology/case-0.6.0-subclasses.ttl
case_utils/ontology/case-0.6.0.ttl
case_utils/ontology/case-0.7.0-subclasses.ttl
case_utils/ontology/case-0.7.0.ttl
case_utils/ontology/case-0.7.1-subclasses.ttl
case_utils/ontology/case-0.7.1.ttl
case_utils/ontology/case-1.0.0-subclasses.ttl
case_utils/ontology/case-1.0.0.ttl
case_utils/ontology/case-1.1.0-subclasses.ttl
case_utils/ontology/case-1.1.0.ttl
case_utils/ontology/case-1.2.0-subclasses.ttl
case_utils/ontology/case-1.2.0.ttl
case_utils/ontology/case-1.3.0-subclasses.ttl
case_utils/ontology/case-1.3.0.ttl
case_utils/ontology/case-1.4.0-subclasses.ttl
case_utils/ontology/case-1.4.0.ttl
case_utils/ontology/ontology_and_version_iris.txt
case_utils/ontology/version_info.py
case_utils-0.17.0.dist-info/licenses/LICENSE
case_utils-0.17.0.dist-info/licenses/THIRD_PARTY_LICENSES.md
case_utils-0.17.0.dist-info/METADATA
case_utils-0.17.0.dist-info/WHEEL
case_utils-0.17.0.dist-info/entry_points.txt
case_utils-0.17.0.dist-info/top_level.txt
case_utils-0.17.0.dist-info/RECORD
